laserbeamsize/__init__.py
laserbeamsize/analysis.py
laserbeamsize/background.py
laserbeamsize/display.py
laserbeamsize/gaussian.py
laserbeamsize/image_tools.py
laserbeamsize/m2_display.py
laserbeamsize/m2_fit.py
laserbeamsize-2.2.0.dist-info/licenses/LICENSE.txt
laserbeamsize-2.2.0.dist-info/METADATA
laserbeamsize-2.2.0.dist-info/WHEEL
laserbeamsize-2.2.0.dist-info/top_level.txt
laserbeamsize-2.2.0.dist-info/RECORD
