Metadata-Version: 2.4
Name: laserbeamsize
Version: 2.2.0
Summary: ISO 11146 Calculation of Laser Beam Center, Diameter, and M²
Author-email: Scott Prahl <scott.prahl@oit.edu>
License-Expression: MIT
Project-URL: Homepage, https://github.com/scottprahl/laserbeamsize
Project-URL: Documentation, https://github.com/scottprahl/laserbeamsize#readme
Project-URL: Source, https://github.com/scottprahl/laserbeamsize
Project-URL: Tracker, https://github.com/scottprahl/laserbeamsize/issues
Project-URL: Changelog, https://github.com/scottprahl/laserbeamsize/blob/main/docs/CHANGELOG.rst
Keywords: variance,gaussian,M-squared,d4sigma,M2,M²,spotsize,laser beam,ISO11146,divergence,beam waist,TEM00,beam diameter,beam parameter product,BPP,laser propagation,beam profiling,beam optics,beam measurement,laser metrology,beam quality,beam analysis
Classifier: Development Status :: 5 - Production/Stable
Classifier: Intended Audience :: Science/Research
Classifier: Programming Language :: Python
Classifier: Programming Language :: Python :: 3.9
Classifier: Programming Language :: Python :: 3.10
Classifier: Programming Language :: Python :: 3.11
Classifier: Programming Language :: Python :: 3.12
Classifier: Programming Language :: Python :: 3.13
Classifier: Topic :: Scientific/Engineering :: Physics
Requires-Python: >=3.9
License-File: LICENSE.txt
Requires-Dist: numpy
Requires-Dist: matplotlib
Requires-Dist: scipy
Dynamic: license-file
